binary_ensemble-0.3.0.dist-info/METADATA
binary_ensemble-0.3.0.dist-info/WHEEL
pyben/__init__.py
pyben/_core.abi3.so
pyben/_core.pyi
pyben/py.typed
binary_ensemble-0.3.0.dist-info/RECORD
