Metadata-Version: 2.4
Name: binary-ensemble
Version: 0.3.0
Requires-Dist: myst-nb>=1.3.0 ; extra == 'docs'
Requires-Dist: myst-parser>=4.0.1 ; extra == 'docs'
Requires-Dist: nbconvert>=7.16.6 ; extra == 'docs'
Requires-Dist: recommonmark>=0.7.1 ; extra == 'docs'
Requires-Dist: sphinx>=8.2.3 ; extra == 'docs'
Requires-Dist: sphinx-autoapi>=3.6.1 ; extra == 'docs'
Requires-Dist: sphinx-copybutton>=0.5.2 ; extra == 'docs'
Requires-Dist: sphinx-rtd-theme>=3.0.2 ; extra == 'docs'
Provides-Extra: docs
Summary: Python bindings for the Binary Ensemble Package.
Requires-Python: >=3.11
